cassandra_migrate/__init__.py
cassandra_migrate/cli.py
cassandra_migrate/config.py
cassandra_migrate/cql.py
cassandra_migrate/migration.py
cassandra_migrate/migrator.py
cassandra_migrate-0.3.4.data/scripts/cassandra-migrate
cassandra_migrate-0.3.4.dist-info/LICENSE
cassandra_migrate-0.3.4.dist-info/METADATA
cassandra_migrate-0.3.4.dist-info/WHEEL
cassandra_migrate-0.3.4.dist-info/top_level.txt
cassandra_migrate-0.3.4.dist-info/RECORD
