Metadata-Version: 2.1
Name: cassandra-migrate
Version: 0.3.4
Summary: Simple Cassandra database migration program.
Home-page: https://github.com/Cobliteam/cassandra-migrate
Author: Daniel Miranda
Author-email: daniel@cobli.co
License: MIT
Download-URL: https://github.com/Cobliteam/cassandra-migrate/archive/0.3.4.tar.gz
Keywords: cassandra schema migration
Platform: UNKNOWN
Requires-Dist: PyYAML (==5.*)
Requires-Dist: arrow (==0.17.0)
Requires-Dist: cassandra-driver (==3.24.0)
Requires-Dist: cassandra-migrate (==0.3.4)
Requires-Dist: click (==7.1.2)
Requires-Dist: future (==0.18.2)
Requires-Dist: geomet (==0.2.1.post1)
Requires-Dist: python-dateutil (==2.8.1)
Requires-Dist: six (==1.15.0)
Requires-Dist: tabulate (==0.8.9)
Requires-Dist: typing-extensions (==3.7.4.3)
